acrod/__init__.py
acrod/jacobian.py
acrod/urdf_to_robottopologymatrix.py
acrod-1.2.0.dist-info/LICENSE
acrod-1.2.0.dist-info/METADATA
acrod-1.2.0.dist-info/WHEEL
acrod-1.2.0.dist-info/top_level.txt
acrod-1.2.0.dist-info/RECORD
