Metadata-Version: 2.1
Name: acrod
Version: 1.2.0
Summary: Automatic Computation for Robot Design (ACRoD)
Author-email: Suneesh Jacob Akkarapakam <suneeshjacob@gmail.com>, Rituparna Datta <rituparndatta@gmail.com>
License: GNU GENERAL PUBLIC LICENSE
Project-URL: Homepage, https://github.com/suneeshjacob/ACRoD
Project-URL: Bug Tracker, https://github.com/suneeshjacob/ACRoD/issues
Project-URL: Source, https://github.com/suneeshjacob/ACRoD/tree/main/src
Keywords: jacobian,robotics,kinematics
Classifier: Programming Language :: Python :: 3
Classifier: License :: OSI Approved :: GNU General Public License v3 (GPLv3)
Classifier: Operating System :: OS Independent
Requires-Python: >=3.7
License-File: LICENSE
Requires-Dist: numpy
Requires-Dist: sympy
